<?xml version="1.0"?>
<opencv_storage>
<stage9>
  <maxWeakCount>8</maxWeakCount>
  <stageThreshold>-1.3179731369018555e+00</stageThreshold>
  <weakClassifiers>
    <_>
      <internalNodes>
        0 -1 134909 -6.2967382371425629e-02</internalNodes>
      <leafValues>
        -2.5691699981689453e-01 -7.7613514661788940e-01</leafValues></_>
    <_>
      <internalNodes>
        0 -1 90989 2.4398235604166985e-02</internalNodes>
      <leafValues>
        -5.2877670526504517e-01 1.2469267845153809e-01</leafValues></_>
    <_>
      <internalNodes>
        0 -1 59255 1.3660754775628448e-03</internalNodes>
      <leafValues>
        1.5222130715847015e-01 -6.0352724790573120e-01</leafValues></_>
    <_>
      <internalNodes>
        0 -1 128966 -1.7125974409282207e-03</internalNodes>
      <leafValues>
        -7.3313295841217041e-01 1.5891072154045105e-01</leafValues></_>
    <_>
      <internalNodes>
        0 -1 9513 -1.8505576997995377e-02</internalNodes>
      <leafValues>
        3.9151039719581604e-01 -2.7891802787780762e-01</leafValues></_>
    <_>
      <internalNodes>
        0 -1 94950 1.8692478537559509e-02</internalNodes>
      <leafValues>
        1.7600646615028381e-01 -6.3359302282333374e-01</leafValues></_>
    <_>
      <internalNodes>
        0 -1 75425 -6.1300516128540039e-02</internalNodes>
      <leafValues>
        -7.5983542203903198e-01 1.0958565771579742e-01</leafValues></_>
    <_>
      <internalNodes>
        0 -1 151657 -7.5068837031722069e-04</internalNodes>
      <leafValues>
        -8.4719973802566528e-01 1.0465567559003830e-01</leafValues></_></weakClassifiers></stage9>
</opencv_storage>
